README.md
requirements.txt
setup.py
nabirds/__init__.py
nabirds.egg-info/PKG-INFO
nabirds.egg-info/SOURCES.txt
nabirds.egg-info/dependency_links.txt
nabirds.egg-info/not-zip-safe
nabirds.egg-info/requires.txt
nabirds.egg-info/top_level.txt
nabirds/annotations/__init__.py
nabirds/annotations/base.py
nabirds/annotations/cars.py
nabirds/annotations/cub.py
nabirds/annotations/inat.py
nabirds/annotations/nab.py
nabirds/dataset/__init__.py
nabirds/dataset/image.py
nabirds/dataset/mixins/__init__.py
nabirds/dataset/mixins/features.py
nabirds/dataset/mixins/parts.py
nabirds/dataset/mixins/postprocess.py
nabirds/dataset/mixins/reading.py
nabirds/dataset/mixins/chainer_mixins/__init__.py
nabirds/dataset/mixins/chainer_mixins/base.py
nabirds/dataset/mixins/chainer_mixins/iterator_mixin.py
nabirds/dataset/part/__init__.py
nabirds/dataset/part/annotation.py
nabirds/dataset/part/base.py
nabirds/dataset/part/collection.py
nabirds/utils/__init__.py
nabirds/utils/image.py