Metadata-Version: 1.0
Name: nabirds
Version: 0.3.2
Summary: Wrapper (inofficial) for NA-Birds bataset (http://dl.allaboutbirds.org/nabirds)
Home-page: UNKNOWN
Author: Dimitri Korsch
Author-email: korschdima@gmail.com
License: MIT License
Platform: UNKNOWN
